MANIFEST.in
README.md
requirements.txt
setup.py
setup_helper.py
treecut.py
scripts/eisen_to_newick.py
scripts/parse_tair_go.py
treecut/__init__.py
treecut/draw.py
treecut/stats.py
treecut/tree.py
treecut/treecut.py
treecut.egg-info/PKG-INFO
treecut.egg-info/SOURCES.txt
treecut.egg-info/dependency_links.txt
treecut.egg-info/requires.txt
treecut.egg-info/top_level.txt