Metadata-Version: 1.1
Name: treecut
Version: 0.7.8
Summary: Find nodes in hierarchical clustering that are statistically significant
Home-page: http://github.com/tanghaibao/treecut
Author: Haibao Tang
Author-email: tanghaibao@gmail.com
License: BSD
Platform: UNKNOWN
Classifier: Development Status :: 4 - Beta
Classifier: Intended Audience :: Science/Research
Classifier: License :: OSI Approved :: BSD License
Classifier: Programming Language :: Python
Classifier: Programming Language :: Python :: 2
Classifier: Topic :: Scientific/Engineering :: Bio-Informatics
